tina_env/envs/__init__.py
tina_env/envs/env_tina.py
tina_env-0.0.1.dist-info/METADATA
tina_env-0.0.1.dist-info/WHEEL
tina_env-0.0.1.dist-info/top_level.txt
tina_env-0.0.1.dist-info/RECORD
