Metadata-Version: 2.1
Name: tina-env
Version: 0.0.1
Summary: A openAI Gym env for tina
Requires-Dist: gym
